[
{"Percentage Decrease in Allergy Symptoms (Drug A)":50},
{"Percentage Decrease in Allergy Symptoms (Drug A)":51},
{"Percentage Decrease in Allergy Symptoms (Drug A)":49},
{"Percentage Decrease in Allergy Symptoms (Drug A)":35},
{"Percentage Decrease in Allergy Symptoms (Drug A)":60},
{"Percentage Decrease in Allergy Symptoms (Drug A)":55},
{"Percentage Decrease in Allergy Symptoms (Drug A)":45},
{"Percentage Decrease in Allergy Symptoms (Drug A)":50},
{"Percentage Decrease in Allergy Symptoms (Drug A)":59},
{"Percentage Decrease in Allergy Symptoms (Drug A)":50},
{"Percentage Decrease in Allergy Symptoms (Drug A)":49},
{"Percentage Decrease in Allergy Symptoms (Drug A)":48},
{"Percentage Decrease in Allergy Symptoms (Drug A)":52},
{"Percentage Decrease in Allergy Symptoms (Drug A)":45},
{"Percentage Decrease in Allergy Symptoms (Drug A)":55},
{"Percentage Decrease in Allergy Symptoms (Drug A)":57},
{"Percentage Decrease in Allergy Symptoms (Drug A)":54},
{"Percentage Decrease in Allergy Symptoms (Drug A)":46},
{"Percentage Decrease in Allergy Symptoms (Drug A)":42},
{"Percentage Decrease in Allergy Symptoms (Drug A)":50}
]
